{
  "manifestVersion": "3.2",
  "admin": {
    "address": "0x1428725B0716811e4E8bE60f08Ed1A8347D16c6b",
    "txHash": "0xf81dea024c47acd44f9415394696e9309f781b0fc1be71ad1a042b6274e1e998"
  },
  "proxies": [
    {
      "address": "0x1df92D6c0Ef1ea101Ca9535E97F9301574FdD702",
      "txHash": "0x724fbdce1f0eb7e7c111a1a1d2ff9c848833e43ab93d970a21625bbc1bbacc9a",
      "kind": "transparent"
    },
    {
      "address": "0x17a2D1AfF979191E207C1A3C1E6c0f71ff5972A4",
      "txHash": "0x2bcd3e0a0778edc0fc871a68b750ed8700a53c58215d2b9d38efc55808855b4e",
      "kind": "transparent"
    },
    {
      "address": "0xBa53E48aEC10fC5474622Af9a699C6637C0EB9Ff",
      "txHash": "0x20f0e2784598d1616eaab2136175ec2eadbd004b6b75d2cddb5128f916b0ded9",
      "kind": "transparent"
    },
    {
      "address": "0xE288323C61B63A19398950f3B74Fd2E1197B89D9",
      "txHash": "0xa5417cd0948595c6668f6317a40427f023ebefc7113f45292279727e6e4a19ec",
      "kind": "transparent"
    },
    {
      "address": "0x31B5e1f00D46a9dEE452eaCcCE42ff1d92AE2BE5",
      "txHash": "0x12c577c7d2493f06f4943f4d7f309e9611c9de556034f197e0bf6f6c6e0f34f0",
      "kind": "transparent"
    },
    {
      "address": "0x6A42e1E9EfB7Ad2DD2765295e8D6f8E56828b117",
      "txHash": "0xc78b9ef38ad50b94df9558109d7b1b96cd7281cd032250b564a1a3c975f88467",
      "kind": "transparent"
    },
    {
      "address": "0x48fa3265eD716444C2BfF77bD9725e179b43b8D4",
      "txHash": "0x0359a2c0bb1f06708da761f78970dd54aa98bb7719b81712d0ade16e47c8b141",
      "kind": "transparent"
    }
  ],
  "impls": {
    "4469a873a9fafe1170300028d7576e125d80dfbfc7541d3ad06d8d27ba0b2fe3": {
      "address": "0x340e3d8b9f7C808ef0A0830334b099A7e863eBF6",
      "txHash": "0x04f2a71cffb305db7c689a062b8427a8e28aa1a7524a0109d84bb9c034d4f128",
      "layout": {
        "storage": [
          {
            "contract": "Initializable",
            "label": "_initialized",
            "type": "t_bool",
            "src": "..\\@openzeppelin\\contracts\\proxy\\utils\\Initializable.sol:21"
          },
          {
            "contract": "Initializable",
            "label": "_initializing",
            "type": "t_bool",
            "src": "..\\@openzeppelin\\contracts\\proxy\\utils\\Initializable.sol:26"
          },
          {
            "contract": "ProxyOwnable",
            "label": "_owner",
            "type": "t_address",
            "src": "..\\project:\\contracts\\ProxyOwnable.sol:20"
          },
          {
            "contract": "REFLECT",
            "label": "_rOwned",
            "type": "t_mapping(t_address,t_uint256)",
            "src": "..\\project:\\contracts\\REFLECT.sol:17"
          },
          {
            "contract": "REFLECT",
            "label": "_tOwned",
            "type": "t_mapping(t_address,t_uint256)",
            "src": "..\\project:\\contracts\\REFLECT.sol:18"
          },
          {
            "contract": "REFLECT",
            "label": "_allowances",
            "type": "t_mapping(t_address,t_mapping(t_address,t_uint256))",
            "src": "..\\project:\\contracts\\REFLECT.sol:19"
          },
          {
            "contract": "REFLECT",
            "label": "_isExcluded",
            "type": "t_mapping(t_address,t_bool)",
            "src": "..\\project:\\contracts\\REFLECT.sol:21"
          },
          {
            "contract": "REFLECT",
            "label": "_excluded",
            "type": "t_array(t_address)dyn_storage",
            "src": "..\\project:\\contracts\\REFLECT.sol:22"
          },
          {
            "contract": "REFLECT",
            "label": "_rTotal",
            "type": "t_uint256",
            "src": "..\\project:\\contracts\\REFLECT.sol:26"
          },
          {
            "contract": "REFLECT",
            "label": "_tFeeTotal",
            "type": "t_uint256",
            "src": "..\\project:\\contracts\\REFLECT.sol:27"
          },
          {
            "contract": "REFLECT",
            "label": "_name",
            "type": "t_string_storage",
            "src": "..\\project:\\contracts\\REFLECT.sol:29"
          },
          {
            "contract": "REFLECT",
            "label": "_symbol",
            "type": "t_string_storage",
            "src": "..\\project:\\contracts\\REFLECT.sol:30"
          },
          {
            "contract": "REFLECT",
            "label": "_decimals",
            "type": "t_uint8",
            "src": "..\\project:\\contracts\\REFLECT.sol:31"
          }
        ],
        "types": {
          "t_mapping(t_address,t_uint256)": {
            "label": "mapping(address => uint256)"
          },
          "t_address": {
            "label": "address"
          },
          "t_uint256": {
            "label": "uint256"
          },
          "t_mapping(t_address,t_mapping(t_address,t_uint256))": {
            "label": "mapping(address => mapping(address => uint256))"
          },
          "t_mapping(t_address,t_bool)": {
            "label": "mapping(address => bool)"
          },
          "t_bool": {
            "label": "bool"
          },
          "t_array(t_address)dyn_storage": {
            "label": "address[]"
          },
          "t_string_storage": {
            "label": "string"
          },
          "t_uint8": {
            "label": "uint8"
          }
        }
      }
    },
    "b56f4e3d0b8d499cdefc1dfcc52a7dfb05923a51a178e6c0e5902d617524ff54": {
      "address": "0x336fc6c4a9cC77351EDE46350153a0B843a35681",
      "txHash": "0xfedd09e427b2f47afb793d7eaf63c9cbb4622a3c2e270752791dfa9d07d020ca",
      "layout": {
        "storage": [
          {
            "contract": "Initializable",
            "label": "_initialized",
            "type": "t_bool",
            "src": "../@openzeppelin/contracts/proxy/utils/Initializable.sol:23"
          },
          {
            "contract": "Initializable",
            "label": "_initializing",
            "type": "t_bool",
            "src": "../@openzeppelin/contracts/proxy/utils/Initializable.sol:28"
          },
          {
            "contract": "ProxyOwnable",
            "label": "_owner",
            "type": "t_address",
            "src": "ProxyOwnable.sol:20"
          },
          {
            "contract": "REFLECT2",
            "label": "_rOwned",
            "type": "t_mapping(t_address,t_uint256)",
            "src": "REFLECT2.sol:17"
          },
          {
            "contract": "REFLECT2",
            "label": "_tOwned",
            "type": "t_mapping(t_address,t_uint256)",
            "src": "REFLECT2.sol:18"
          },
          {
            "contract": "REFLECT2",
            "label": "_allowances",
            "type": "t_mapping(t_address,t_mapping(t_address,t_uint256))",
            "src": "REFLECT2.sol:19"
          },
          {
            "contract": "REFLECT2",
            "label": "_isExcluded",
            "type": "t_mapping(t_address,t_bool)",
            "src": "REFLECT2.sol:21"
          },
          {
            "contract": "REFLECT2",
            "label": "_excluded",
            "type": "t_array(t_address)dyn_storage",
            "src": "REFLECT2.sol:22"
          },
          {
            "contract": "REFLECT2",
            "label": "_rTotal",
            "type": "t_uint256",
            "src": "REFLECT2.sol:26"
          },
          {
            "contract": "REFLECT2",
            "label": "_tFeeTotal",
            "type": "t_uint256",
            "src": "REFLECT2.sol:27"
          },
          {
            "contract": "REFLECT2",
            "label": "_name",
            "type": "t_string_storage",
            "src": "REFLECT2.sol:29"
          },
          {
            "contract": "REFLECT2",
            "label": "_symbol",
            "type": "t_string_storage",
            "src": "REFLECT2.sol:30"
          },
          {
            "contract": "REFLECT2",
            "label": "_decimals",
            "type": "t_uint8",
            "src": "REFLECT2.sol:31"
          }
        ],
        "types": {
          "t_mapping(t_address,t_uint256)": {
            "label": "mapping(address => uint256)"
          },
          "t_address": {
            "label": "address"
          },
          "t_uint256": {
            "label": "uint256"
          },
          "t_mapping(t_address,t_mapping(t_address,t_uint256))": {
            "label": "mapping(address => mapping(address => uint256))"
          },
          "t_mapping(t_address,t_bool)": {
            "label": "mapping(address => bool)"
          },
          "t_bool": {
            "label": "bool"
          },
          "t_array(t_address)dyn_storage": {
            "label": "address[]"
          },
          "t_string_storage": {
            "label": "string"
          },
          "t_uint8": {
            "label": "uint8"
          }
        }
      }
    }
  }
}
